<?xml version="1.0" encoding="UTF-8"?>
<!DOCTYPE properties SYSTEM "http://java.sun.com/dtd/properties.dtd">
<properties>
<comment></comment>
<entry key="ownerExternalKey">31d4df1f-5378-4d28-9b71-c7799d6e7905</entry>
<entry key="version"></entry>
<entry key="localeType">0</entry>
<entry key="name">pageGuid</entry>
<entry key="lastModified">1408566418808</entry>
<entry key="value">2e91f438-52c0-43d0-8338-abce9b6a1bce</entry>
<entry key="overwriteFromUrl">0</entry>
<entry key="externalKey">933a96a6-08cf-45c0-a024-b7eb384e4280</entry>
</properties>
